cloudflare_ai/__init__.py
cloudflare_ai/server.py
cloudflare_ai/testpypi.md
cloudflare_ai/tools/__init__.py
cloudflare_ai/tools/generate_images.py
cloudflare_ai/tools/generate_prompt.py
cloudflare_ai/utils/__init__.py
cloudflare_ai/utils/cloudflare.py
cloudflare_ai_mcp-0.1.0.dist-info/METADATA
cloudflare_ai_mcp-0.1.0.dist-info/WHEEL
cloudflare_ai_mcp-0.1.0.dist-info/RECORD
