Metadata-Version: 2.4
Name: cloudflare-ai-mcp
Version: 0.1.0
Summary: MCP Server for Cloudflare AI image generation
Author-email: ouraihub <ouraihub@gmail.com>
License: MIT
Requires-Python: >=3.10
Requires-Dist: aiohttp>=3.9.3
Requires-Dist: cloudflare>=2.8.15
Requires-Dist: pillow>=10.2.0
Requires-Dist: python-dotenv>=1.0.1
Requires-Dist: requests>=2.31.0
Requires-Dist: streamlit>=1.31.1
Requires-Dist: uvicorn>=0.15.0
